Metadata-Version: 2.1
Name: housing_library_5494
Version: 0.1
Summary: Sample code for coding practice
Author-email: shannu2205 <shanmukha.nallur@tigeranalytics.com>
Project-URL: Homepage, https://github.com/shannu2205/mle-training
Keywords: housing,data training
Classifier: Programming Language :: Python :: 3
Requires-Python: >=3.11
Requires-Dist: numpy
Requires-Dist: pandas
Requires-Dist: scikit-learn
